README.md
setup.py
handout/__init__.py
handout/blocks.py
handout/handout.py
handout/tools.py
handout.egg-info/PKG-INFO
handout.egg-info/SOURCES.txt
handout.egg-info/dependency_links.txt
handout.egg-info/requires.txt
handout.egg-info/top_level.txt
handout/data/favicon.ico
handout/data/highlight.css
handout/data/highlight.js
handout/data/marked.js
handout/data/script.js
handout/data/style.css