Metadata-Version: 2.1
Name: handout
Version: 1.1.2
Summary: Turn Python scripts into handouts with Markdown and figures
Home-page: http://github.com/danijar/handout
License: UNKNOWN
Platform: UNKNOWN
Classifier: Programming Language :: Python :: 3
Classifier: Topic :: Scientific/Engineering :: Visualization
Classifier: Topic :: Multimedia :: Graphics :: Presentation
Classifier: License :: OSI Approved :: Apache Software License
Provides-Extra: media
